terminal_snake_game/__init__.py
terminal_snake_game-1.0.4.dist-info/METADATA
terminal_snake_game-1.0.4.dist-info/WHEEL
terminal_snake_game-1.0.4.dist-info/entry_points.txt
terminal_snake_game-1.0.4.dist-info/top_level.txt
terminal_snake_game-1.0.4.dist-info/RECORD
