Metadata-Version: 2.4
Name: terminal_snake_game
Version: 1.0.4
Summary: A classic Snake game implementation in Python using curses
Home-page: https://github.com/SwetaTanwar/snake-game
Author: Sweta Tanwar
Author-email: shweta_tanwar@ymail.com
Classifier: Programming Language :: Python :: 3
Classifier: License :: OSI Approved :: MIT License
Classifier: Operating System :: OS Independent
Requires-Python: >=3.6
Provides-Extra: test
Requires-Dist: pytest>=7.0.0; extra == "test"
Requires-Dist: pytest-cov>=4.0.0; extra == "test"
Dynamic: author
Dynamic: author-email
Dynamic: classifier
Dynamic: description
Dynamic: description-content-type
Dynamic: home-page
Dynamic: provides-extra
Dynamic: requires-python
Dynamic: summary
